fair/__init__.py
fair/client.py
faircompute-0.22.1.dist-info/LICENSE
faircompute-0.22.1.dist-info/METADATA
faircompute-0.22.1.dist-info/WHEEL
faircompute-0.22.1.dist-info/top_level.txt
faircompute-0.22.1.dist-info/RECORD
