Metadata-Version: 2.1
Name: faircompute
Version: 0.22.1
Summary: A Python client for FairCompute API
Author-email: Dmitry Trifonov <dtrifonov@faircompute.com>
Project-URL: Homepage, https://faircompute.com
Project-URL: Issues, https://discord.gg/zFtVVrSdUz
Classifier: Programming Language :: Python :: 3
Classifier: License :: OSI Approved :: MIT License
Classifier: Operating System :: OS Independent
Requires-Python: >=3.8
License-File: LICENSE
Requires-Dist: requests[security] <3
